README.md
setup.py
pydbwrapper/__init__.py
pydbwrapper/config.py
pydbwrapper/database.py
pydbwrapper.egg-info/PKG-INFO
pydbwrapper.egg-info/SOURCES.txt
pydbwrapper.egg-info/dependency_links.txt
pydbwrapper.egg-info/requires.txt
pydbwrapper.egg-info/top_level.txt
test/__init__.py
test/database-test.py